[ {
  "id" : "6385e188-e301-20fb-e340-67be9e1a0980",
  "name" : "ctas",
  "display_width" : null,
  "label" : "CTAs",
  "required" : false,
  "locked" : false,
  "occurrence" : {
    "min" : null,
    "max" : null,
    "sorting_label_field" : null,
    "default" : null
  },
  "children" : [ {
    "id" : "76f21217-5b2c-10a0-662f-da20c77cb883",
    "name" : "text",
    "display_width" : null,
    "label" : "Text",
    "required" : true,
    "locked" : false,
    "validation_regex" : "",
    "allow_new_line" : false,
    "show_emoji_picker" : false,
    "type" : "text",
    "default" : "CTA Text"
  }, {
    "id" : "9ca75564-4085-f79e-4f19-3c0e5899d134",
    "name" : "url",
    "display_width" : null,
    "label" : "URL",
    "required" : false,
    "locked" : false,
    "supported_types" : [ "EXTERNAL", "CONTENT", "FILE", "EMAIL_ADDRESS", "BLOG", "CALL_TO_ACTION", "PHONE_NUMBER", "WHATSAPP_NUMBER", "PAYMENT" ],
    "type" : "url",
    "default" : {
      "content_id" : null,
      "href" : "",
      "type" : "EXTERNAL"
    }
  }, {
    "id" : "a5fb5961-6f4b-1911-8d9c-673b8446e0b5",
    "name" : "style",
    "display_width" : null,
    "label" : "Style",
    "required" : true,
    "locked" : false,
    "display" : "select",
    "choices" : [ [ "btn", "Button" ], [ "text", "Text" ] ],
    "multiple" : false,
    "reordering_enabled" : true,
    "preset" : null,
    "type" : "choice",
    "default" : "btn"
  }, {
    "id" : "bef2b72d-69e6-a367-c379-1aa83bc9a92d",
    "name" : "color",
    "display_width" : null,
    "label" : "Color",
    "required" : true,
    "locked" : false,
    "display" : "select",
    "choices" : [ [ "black", "Black" ], [ "blue", "Blue" ], [ "white", "White" ] ],
    "multiple" : false,
    "reordering_enabled" : true,
    "preset" : null,
    "type" : "choice",
    "default" : "blue"
  }, {
    "id" : "f74215c7-f95a-98c1-6732-c121862b7d0a",
    "name" : "new_window",
    "display_width" : null,
    "label" : "New window",
    "help_text" : "Does link open on a new window?",
    "required" : false,
    "locked" : false,
    "display" : "toggle",
    "type" : "boolean",
    "default" : false
  } ],
  "tab" : "CONTENT",
  "expanded" : false,
  "group_occurrence_meta" : null,
  "type" : "group",
  "default" : [ ]
}, {
  "id" : "6586ba60-a429-a606-20ae-80207850c3d7",
  "name" : "margin_top",
  "display_width" : null,
  "label" : "Margin - Top",
  "required" : false,
  "locked" : false,
  "table_name_or_id" : "29821205",
  "columns_to_fetch" : [ "spacing" ],
  "display_columns" : [ "spacing" ],
  "type" : "hubdbrow",
  "default" : {
    "id" : 180327934732
  }
}, {
  "id" : "a0cd552b-4f12-a832-feae-8f07f9373d8e",
  "name" : "margin_bottom",
  "display_width" : null,
  "label" : "Margin - Bottom",
  "required" : false,
  "locked" : false,
  "table_name_or_id" : "29821205",
  "columns_to_fetch" : [ "spacing" ],
  "display_columns" : [ "spacing" ],
  "type" : "hubdbrow",
  "default" : {
    "id" : 180327934732
  }
}, {
  "id" : "250759e9-f4c1-19dc-7850-dbeeada16edf",
  "name" : "center_horizontally",
  "display_width" : null,
  "label" : "Center Horizontally",
  "required" : false,
  "locked" : false,
  "display" : "toggle",
  "type" : "boolean",
  "default" : false
} ]